FastVCD/__init__.py
FastVCD/fastvcd.py
fastvcd_pkg_rishubn-0.0.1.dist-info/LICENSE
fastvcd_pkg_rishubn-0.0.1.dist-info/METADATA
fastvcd_pkg_rishubn-0.0.1.dist-info/WHEEL
fastvcd_pkg_rishubn-0.0.1.dist-info/top_level.txt
fastvcd_pkg_rishubn-0.0.1.dist-info/RECORD
